ipynta/__init__.py
ipynta/enums/__init__.py
ipynta/enums/naming_strategy.py
ipynta/loaders/__init__.py
ipynta/loaders/opencv_loader.py
ipynta/loaders/pillow_loader.py
ipynta/packaging/__init__.py
ipynta/packaging/tar_packager.py
ipynta/packaging/zip_packager.py
ipynta/persistence/__init__.py
ipynta/persistence/local_persister.py
ipynta/predicates/__init__.py
ipynta/predicates/base.py
ipynta/predicates/dimension.py
ipynta/predicates/file_ext.py
ipynta/predicates/grayscale.py
ipynta/predicates/true_file_type.py
ipynta/sourcing/__init__.py
ipynta/sourcing/directory_sniffer.py
ipynta/sourcing/download_keypair.py
ipynta/sourcing/http_downloader.py
ipynta/sourcing/s3_downloader.py
ipynta/transform/__init__.py
ipynta/transform/base.py
ipynta/transform/grayscale.py
ipynta/transform/hflip.py
ipynta/transform/vflip.py
ipynta/validators/__init__.py
ipynta/validators/string_validator.py
ipynta-0.0.40.dist-info/METADATA
ipynta-0.0.40.dist-info/WHEEL
ipynta-0.0.40.dist-info/top_level.txt
ipynta-0.0.40.dist-info/RECORD
