Metadata-Version: 2.1
Name: ipynta
Version: 0.0.40
Summary: A Python library for different image processing tasks.
Home-page: UNKNOWN
Author: Allan Chua
Author-email: allanchua.officefiles@gmail.com
License: UNKNOWN
Project-URL: Source Code, https://github.com/allanchua101/ipynta
Keywords: python,images,image utilities
Platform: UNKNOWN
Classifier: Development Status :: 1 - Planning
Classifier: Intended Audience :: Developers
Classifier: Programming Language :: Python :: 3
Classifier: Operating System :: Unix
Classifier: Operating System :: MacOS :: MacOS X
Classifier: Operating System :: Microsoft :: Windows
Requires-Dist: pillow
Requires-Dist: numpy
